napari_demo/__init__.py
napari_demo/_version.py
napari_demo/napari.yaml
napari_demo/_tests/__init__.py
napari_demo-0.2.5.dist-info/LICENSE
napari_demo-0.2.5.dist-info/METADATA
napari_demo-0.2.5.dist-info/WHEEL
napari_demo-0.2.5.dist-info/entry_points.txt
napari_demo-0.2.5.dist-info/top_level.txt
napari_demo-0.2.5.dist-info/RECORD
