Metadata-Version: 2.1
Name: napari-demo
Version: 0.2.5
Summary: example plugin for napari plugin developers
Home-page: https://github.com/chanzuckerberg/napari-demo
Author: napari hub team
Author-email: team@napari-hub.org
License: BSD-3
Project-URL: Source Code, https://github.com/chanzuckerberg/napari-demo
Classifier: Development Status :: 4 - Beta
Classifier: Intended Audience :: Developers
Classifier: License :: OSI Approved :: BSD License
Classifier: Programming Language :: Python
Classifier: Programming Language :: Python :: 3 :: Only
Classifier: Programming Language :: Python :: 3.8
Classifier: Programming Language :: Python :: 3.9
Classifier: Programming Language :: Python :: 3.10
Classifier: Topic :: Software Development :: Testing
Classifier: Operating System :: OS Independent
Classifier: Framework :: napari
Requires-Python: >=3.7
License-File: LICENSE
Requires-Dist: pydantic
Requires-Dist: npe2
Requires-Dist: numpy
